coreax/__init__.py
coreax/approximation.py
coreax/benchmark_util.py
coreax/coreset.py
coreax/data.py
coreax/least_squares.py
coreax/metrics.py
coreax/networks.py
coreax/py.typed
coreax/score_matching.py
coreax/util.py
coreax/weights.py
coreax/kernels/__init__.py
coreax/kernels/base.py
coreax/kernels/scalar_valued.py
coreax/kernels/util.py
coreax/solvers/__init__.py
coreax/solvers/base.py
coreax/solvers/composite.py
coreax/solvers/coresubset.py
coreax/solvers/recombination.py
coreax-1.0.0.dist-info/licenses/LICENSE
coreax-1.0.0.dist-info/METADATA
coreax-1.0.0.dist-info/WHEEL
coreax-1.0.0.dist-info/top_level.txt
coreax-1.0.0.dist-info/RECORD
