Metadata-Version: 2.4
Name: coreax
Version: 1.0.0
Summary: Jax coreset algorithms.
Author-email: GCHQ <oss@gchq.gov.uk>
License: 
Project-URL: Documentation, https://coreax.readthedocs.io/en/latest/
Project-URL: Repository, https://github.com/gchq/coreax
Project-URL: Issues, https://github.com/gchq/coreax/issues
Project-URL: Changelog, https://github.com/gchq/coreax/blob/main/CHANGELOG.md
Keywords: coreset
Classifier: Development Status :: 5 - Production/Stable
Classifier: Programming Language :: Python
Classifier: Programming Language :: Python :: 3.9
Classifier: Programming Language :: Python :: 3.10
Classifier: Programming Language :: Python :: 3.11
Classifier: Programming Language :: Python :: 3.12
Classifier: Programming Language :: Python :: 3.13
Classifier: Typing :: Typed
Requires-Python: >=3.9
License-File: LICENSE
Requires-Dist: equinox>=0.11.5
Requires-Dist: flax>=0.8
Requires-Dist: jax>=0.4
Requires-Dist: jaxopt>=0.8
Requires-Dist: jaxtyping>0.2.31
Requires-Dist: optax>=0.2
Requires-Dist: scikit-learn>=1
Requires-Dist: tqdm>=4
Requires-Dist: typing-extensions>=4.12
Provides-Extra: example
Requires-Dist: imageio>=2; extra == "example"
Requires-Dist: matplotlib>=3; extra == "example"
Requires-Dist: numpy>=2; extra == "example"
Requires-Dist: opencv-python-headless>=4; extra == "example"
Provides-Extra: benchmark
Requires-Dist: coreax[example]; extra == "benchmark"
Requires-Dist: torch>=2.5; extra == "benchmark"
Requires-Dist: torchvision>=0.20; extra == "benchmark"
Requires-Dist: umap-learn>=0.5.7; extra == "benchmark"
Requires-Dist: llvmlite>=0.40.0; extra == "benchmark"
Provides-Extra: test
Requires-Dist: coreax[benchmark]; extra == "test"
Requires-Dist: beartype!=0.20.1,!=0.20.2,>=0.19; extra == "test"
Requires-Dist: pytest>=8; extra == "test"
Requires-Dist: pytest-cov>=6; extra == "test"
Requires-Dist: pytest-rerunfailures>=15; extra == "test"
Requires-Dist: pytest-xdist>=3; extra == "test"
Requires-Dist: scipy>=1.13; extra == "test"
Provides-Extra: doc
Requires-Dist: furo>=2024; extra == "doc"
Requires-Dist: sphinx>=7; extra == "doc"
Requires-Dist: sphinx-autodoc-typehints>=2; extra == "doc"
Requires-Dist: sphinx-toolbox>=3; extra == "doc"
Requires-Dist: sphinxcontrib-bibtex>=2; extra == "doc"
Requires-Dist: sphobjinv>=2; extra == "doc"
Dynamic: license-file
